<?xml version="1.0" encoding="UTF-8"?>
<!DOCTYPE suite SYSTEM "http://testng.org/testng-1.0.dtd">
<suite name="Orange HRM Test Suite" parallel="none">


	<listeners>
		<listener class-name="com.HRM.ExtentReportListener.ExtentReporterNG" />
	</listeners>


	<test name="Orange HRM Test Cases" 	preserve-order="false">
		<classes>
			<class name="com.HRM.testcases.LoginPageTest"></class>
			<class name="com.HRM.testcases.AdminHomePageTest"></class>
			<class name="com.HRM.testcases.AdminModulePageTest"></class>
			<class name="com.HRM.testcases.UsersPageTest"></class>
			<class name="com.HRM.testcases.PIMPageTest"></class>
			<class name="com.HRM.testcases.LeavePageTest"></class>
			<class name="com.HRM.testcases.TimePageTest"></class>
			<class name="com.HRM.testcases.RecruitmentPageTest"></class>
			<class name="com.HRM.testcases.PerformancePageTest"></class>
			<class name="com.HRM.testcases.AddJobTitlePageTest"></class>
			<class name="com.HRM.testcases.JobTitlesPageTest"></class>			
			<class name="com.HRM.testcases.AddPayGradePageTest"></class>
			<class name="com.HRM.testcases.PayGradesPageTest"></class>			
			<class name="com.HRM.testcases.EmploymentStatusPageTest"></class>			
			<class name="com.HRM.testcases.JobCategoriesPageTest"></class>			
			<class name="com.HRM.testcases.GeneralInformationPageTest"></class>						
			<class name="com.HRM.testcases.AddLocationPageTest"></class>
			<class name="com.HRM.testcases.LocationsPageTest"></class>
			<class name="com.HRM.testcases.StructurePageTest"></class>
			<class name="com.HRM.testcases.SkillsPageTest"></class>			
			<class name="com.HRM.testcases.EducationPageTest"></class>			
			<class name="com.HRM.testcases.LicensesPageTest"></class>
			<class name="com.HRM.testcases.LanguagePageTest"></class>				
		</classes>
	</test>
</suite>